char_frequency_lib/__init__.py
char_frequency_lib/__main__.py
char_frequency_lib/core.py
charfrequencylib-0.1.0.dist-info/licenses/LICENSE
charfrequencylib-0.1.0.dist-info/METADATA
charfrequencylib-0.1.0.dist-info/WHEEL
charfrequencylib-0.1.0.dist-info/entry_points.txt
charfrequencylib-0.1.0.dist-info/top_level.txt
charfrequencylib-0.1.0.dist-info/RECORD
