Metadata-Version: 2.4
Name: CharFrequencyLib
Version: 0.1.0
Summary: Calculate character frequency in text
Author: Ashjan Walid Alakhaly
Author-email: Ashjan Walid Alakhaly <alakhaly58@gmail.com>
License: MIT License
Requires-Python: >=3.7
License-File: LICENSE
Dynamic: author
Dynamic: license-file
Dynamic: requires-python
